cloud_volume-12.9.0.dist-info/licenses/AUTHORS
cloud_volume-12.9.0.dist-info/licenses/LICENSE
cloudvolume/__init__.py
cloudvolume/cacheservice.py
cloudvolume/chunks.py
cloudvolume/cloudvolume.py
cloudvolume/compression.py
cloudvolume/connectionpools.py
cloudvolume/dask.py
cloudvolume/exceptions.py
cloudvolume/lib.py
cloudvolume/lru.py
cloudvolume/mesh.py
cloudvolume/paths.py
cloudvolume/provenance.py
cloudvolume/scheduler.py
cloudvolume/secrets.py
cloudvolume/server.py
cloudvolume/sharedmemory.py
cloudvolume/skeleton.py
cloudvolume/threaded_queue.py
cloudvolume/types.py
cloudvolume/volumecutout.py
cloudvolume/datasource/__init__.py
cloudvolume/datasource/boss/__init__.py
cloudvolume/datasource/boss/image.py
cloudvolume/datasource/boss/metadata.py
cloudvolume/datasource/graphene/__init__.py
cloudvolume/datasource/graphene/metadata.py
cloudvolume/datasource/graphene/sharding.py
cloudvolume/datasource/graphene/mesh/__init__.py
cloudvolume/datasource/graphene/mesh/metadata.py
cloudvolume/datasource/graphene/mesh/sharded.py
cloudvolume/datasource/graphene/mesh/unsharded.py
cloudvolume/datasource/n5/__init__.py
cloudvolume/datasource/n5/image.py
cloudvolume/datasource/n5/metadata.py
cloudvolume/datasource/precomputed/__init__.py
cloudvolume/datasource/precomputed/common.py
cloudvolume/datasource/precomputed/metadata.py
cloudvolume/datasource/precomputed/mmh3.py
cloudvolume/datasource/precomputed/sharding.py
cloudvolume/datasource/precomputed/spatial_index.py
cloudvolume/datasource/precomputed/annotation/__init__.py
cloudvolume/datasource/precomputed/annotation/metadata.py
cloudvolume/datasource/precomputed/annotation/reader.py
cloudvolume/datasource/precomputed/image/__init__.py
cloudvolume/datasource/precomputed/image/common.py
cloudvolume/datasource/precomputed/image/rx.py
cloudvolume/datasource/precomputed/image/tx.py
cloudvolume/datasource/precomputed/image/xfer.py
cloudvolume/datasource/precomputed/mesh/__init__.py
cloudvolume/datasource/precomputed/mesh/common.py
cloudvolume/datasource/precomputed/mesh/metadata.py
cloud_volume-12.9.0.dist-info/METADATA
cloud_volume-12.9.0.dist-info/WHEEL
cloud_volume-12.9.0.dist-info/top_level.txt
cloud_volume-12.9.0.dist-info/RECORD
