Metadata-Version: 2.4
Name: cloud_volume
Version: 12.9.0
Summary: A serverless client for reading and writing Neuroglancer Precomputed volumes both locally and on cloud services.
Home-page: https://github.com/seung-lab/cloud-volume/
Author: William Silversmith, Nico Kemnitz, Ignacio Tartavull, and others
Author-email: ws9@princeton.edu
License: BSD-3-Clause
Keywords: neuroglancer volumetric-data numpy connectomics microscopy image-processing biomedical-image-processing s3 gcs mesh meshes skeleton skeletons
Classifier: Intended Audience :: Developers
Classifier: Development Status :: 5 - Production/Stable
Classifier: Programming Language :: Python
Classifier: Programming Language :: Python :: 3
Classifier: Programming Language :: Python :: 3.8
Classifier: Programming Language :: Python :: 3.9
Classifier: Programming Language :: Python :: 3.10
Classifier: Programming Language :: Python :: 3.11
Classifier: Programming Language :: Python :: 3.12
Classifier: Programming Language :: Python :: 3.13
Classifier: Programming Language :: Python :: 3.14
Classifier: Topic :: Scientific/Engineering
Classifier: Intended Audience :: Science/Research
Classifier: Operating System :: POSIX
Classifier: Operating System :: MacOS
Classifier: Operating System :: Microsoft :: Windows :: Windows 10
Classifier: Topic :: Utilities
Requires-Python: >=3.8
License-File: LICENSE
License-File: AUTHORS
Requires-Dist: boto3>=1.4.7
Requires-Dist: chardet>=3.0.4
Requires-Dist: cloud-files<6.0.0,>=4.29.0
Requires-Dist: compressed-segmentation>=2.3.2
Requires-Dist: DracoPy<2.0.0,>=1.0.0
Requires-Dist: fastremap>=1.17.4
Requires-Dist: gevent
Requires-Dist: google-auth>=1.10.0
Requires-Dist: google-cloud-core>=1.1.0
Requires-Dist: google-cloud-storage>=1.24.1
Requires-Dist: json5
Requires-Dist: jsonschema!=4.0
Requires-Dist: microviewer
Requires-Dist: numpy>=1.13.3
Requires-Dist: networkx
Requires-Dist: osteoid
Requires-Dist: python-jsonschema-objects>=0.3.3
Requires-Dist: pathos
Requires-Dist: protobuf>=3.3.0
Requires-Dist: python-dateutil
Requires-Dist: requests>=2.22.0
Requires-Dist: psutil
Requires-Dist: pysimdjson>=3.1.1
Requires-Dist: simplejpeg
Requires-Dist: tenacity>=4.10.0
Requires-Dist: tqdm
Requires-Dist: urllib3[brotli]>=1.25.7
Provides-Extra: boss
Requires-Dist: intern>=0.9.11; extra == "boss"
Requires-Dist: blosc; extra == "boss"
Requires-Dist: posix_ipc>=1.0.4; sys_platform != "win32"
Requires-Dist: psutil>=5.4.3; sys_platform != "win32"
Provides-Extra: mesh-viewer
Requires-Dist: vtk; extra == "mesh-viewer"
Provides-Extra: skeleton-viewer
Requires-Dist: matplotlib>=3.6; extra == "skeleton-viewer"
Provides-Extra: all-viewers
Requires-Dist: vtk; extra == "all-viewers"
Requires-Dist: matplotlib>=3.6; extra == "all-viewers"
Provides-Extra: dask
Requires-Dist: dask[array]; extra == "dask"
Provides-Extra: zarr
Requires-Dist: blosc; extra == "zarr"
Requires-Dist: zstandard; extra == "zarr"
Provides-Extra: test
Requires-Dist: pytest; extra == "test"
Requires-Dist: pytest-cov; extra == "test"
Requires-Dist: codecov; extra == "test"
Requires-Dist: requests_mock; extra == "test"
Requires-Dist: scipy; extra == "test"
Requires-Dist: zarr; extra == "test"
Requires-Dist: blosc; extra == "test"
Requires-Dist: zstandard; extra == "test"
Provides-Extra: psql
Requires-Dist: psycopg2; extra == "psql"
Provides-Extra: mysql
Requires-Dist: mysql-connector-python; extra == "mysql"
Provides-Extra: all-sql
Requires-Dist: psycopg2; extra == "all-sql"
Requires-Dist: mysql-connector-python; extra == "all-sql"
Provides-Extra: blosc
Requires-Dist: blosc; extra == "blosc"
Provides-Extra: jxl
Requires-Dist: imagecodecs; extra == "jxl"
Provides-Extra: png
Requires-Dist: pyspng-seunglab; extra == "png"
Provides-Extra: jpeg
Requires-Dist: simplejpeg; extra == "jpeg"
Provides-Extra: fpzip
Requires-Dist: fpzip; extra == "fpzip"
Provides-Extra: zfpc
Requires-Dist: zfpc; extra == "zfpc"
Provides-Extra: crackle
Requires-Dist: crackle-codec; extra == "crackle"
Provides-Extra: compresso
Requires-Dist: compresso; extra == "compresso"
Provides-Extra: em-codecs
Requires-Dist: imagecodecs; extra == "em-codecs"
Requires-Dist: simplejpeg; extra == "em-codecs"
Requires-Dist: pyspng-seunglab>=1.0.0; extra == "em-codecs"
Provides-Extra: seg-codecs
Requires-Dist: compressed-segmentation>=2.1.1; extra == "seg-codecs"
Requires-Dist: compresso>=3.0.0; extra == "seg-codecs"
Requires-Dist: crackle-codec<2.0.0,>=0.8.0; extra == "seg-codecs"
Provides-Extra: fp-codecs
Requires-Dist: fpzip; extra == "fp-codecs"
Requires-Dist: zfpc; extra == "fp-codecs"
Provides-Extra: all-codecs
Requires-Dist: compressed-segmentation>=2.1.1; extra == "all-codecs"
Requires-Dist: compresso>=3.0.0; extra == "all-codecs"
Requires-Dist: crackle-codec<2.0.0,>=0.8.0; extra == "all-codecs"
Requires-Dist: imagecodecs; extra == "all-codecs"
Requires-Dist: simplejpeg; extra == "all-codecs"
Requires-Dist: pyspng-seunglab>=1.0.0; extra == "all-codecs"
Requires-Dist: fpzip; extra == "all-codecs"
Requires-Dist: zfpc; extra == "all-codecs"
Requires-Dist: blosc; extra == "all-codecs"
Requires-Dist: intern; extra == "all-codecs"
Requires-Dist: zstandard; extra == "all-codecs"
Provides-Extra: all
Requires-Dist: compressed-segmentation>=2.1.1; extra == "all"
Requires-Dist: compresso>=3.0.0; extra == "all"
Requires-Dist: crackle-codec<2.0.0,>=0.8.0; extra == "all"
Requires-Dist: imagecodecs; extra == "all"
Requires-Dist: simplejpeg; extra == "all"
Requires-Dist: pyspng-seunglab>=1.0.0; extra == "all"
Requires-Dist: fpzip; extra == "all"
Requires-Dist: zfpc; extra == "all"
Requires-Dist: blosc; extra == "all"
Requires-Dist: intern; extra == "all"
Requires-Dist: zstandard; extra == "all"
Requires-Dist: dask[array]; extra == "all"
Requires-Dist: vtk; extra == "all"
Requires-Dist: matplotlib; extra == "all"
Requires-Dist: pytest; extra == "all"
Requires-Dist: pytest-cov; extra == "all"
Requires-Dist: codecov; extra == "all"
Requires-Dist: requests_mock; extra == "all"
Requires-Dist: scipy; extra == "all"
Requires-Dist: pillow; extra == "all"
Requires-Dist: psycopg2; extra == "all"
Requires-Dist: mysql-connector-python; extra == "all"
Dynamic: author
Dynamic: author-email
Dynamic: classifier
Dynamic: description
Dynamic: description-content-type
Dynamic: home-page
Dynamic: keywords
Dynamic: license
Dynamic: license-file
Dynamic: provides-extra
Dynamic: requires-dist
Dynamic: requires-python
Dynamic: summary
